sentinel_logger/__init__.py
sentinel_logger/django.py
sentinel_logger/middleware.py
sentinel_logger/middleware_asgi.py
sentinel_logger-0.1.0.dist-info/METADATA
sentinel_logger-0.1.0.dist-info/WHEEL
sentinel_logger-0.1.0.dist-info/top_level.txt
sentinel_logger-0.1.0.dist-info/RECORD
